scad2gltf/__init__.py
scad2gltf/__main__.py
scad2gltf/gltf.py
scad2gltf-0.0.3.dist-info/METADATA
scad2gltf-0.0.3.dist-info/WHEEL
scad2gltf-0.0.3.dist-info/entry_points.txt
scad2gltf-0.0.3.dist-info/licenses/LICENSE
scad2gltf-0.0.3.dist-info/RECORD
