Metadata-Version: 2.4
Name: scad2gltf
Version: 0.0.3
Summary: Create GLTF files from OpenSCAD files.
Project-URL: Homepage, https://gitbuilding.io/
Project-URL: Bug Tracker, https://gitlab.com/bath_open_instrumentation_group/scad2gltf/issues
Project-URL: Source Code, https://gitlab.com/bath_open_instrumentation_group/scad2gltf
Author-email: Julian Stirling <julian@julianstirling.co.uk>
License-File: LICENSE
Keywords: GLTF,OpenSCAD,conversion
Classifier: Development Status :: 5 - Production/Stable
Classifier: License :: OSI Approved :: GNU General Public License v3 (GPLv3)
Classifier: Programming Language :: Python :: 3.6
Requires-Python: >=3.6
Requires-Dist: numpy
Requires-Dist: numpy-stl
Requires-Dist: pygltflib
Requires-Dist: regex
